scaffoldpy/__init__.py
scaffoldpy/__version__.py
scaffoldpy/builders.py
scaffoldpy/cli.py
scaffoldpy/consts.py
scaffoldpy/models.py
scaffoldpy/_config/config_scaffoldpy.json5
scaffoldpy/_config/scaffoldpy.code-workspace
scaffoldpy/_config/schema_scaffoldpy.json
scaffoldpy-0.0.0.dist-info/METADATA
scaffoldpy-0.0.0.dist-info/WHEEL
scaffoldpy-0.0.0.dist-info/entry_points.txt
scaffoldpy-0.0.0.dist-info/licenses/LICENSE
scaffoldpy-0.0.0.dist-info/RECORD
