Metadata-Version: 2.4
Name: scaffoldpy
Version: 0.0.0
Dynamic: Description
Dynamic: Description-Content-Type
Summary: A cli tool to create a Python project with best practices
Project-URL: Homepage, https://github.com/austinyu/scaffoldpy
Project-URL: Source, https://github.com/austinyu/scaffoldpy
Project-URL: Issues, https://todo.com
Author-email: Austin Yu <yuxm.austin1023@gmail.com>
Maintainer-email: Austin Yu <yuxm.austin1023@gmail.com>
License: MIT
License-File: LICENSE
Requires-Python: >=3.10
Requires-Dist: inquirerpy>=0.3.4
Requires-Dist: pydantic>=2.10.6
Requires-Dist: toml>=0.10.2
Requires-Dist: types-toml>=0.10.8.20240310
Requires-Dist: ujson5>=1.0.1
